{
  "slug": "omut",
  "index": "02",
  "title": "OMUT",
  "next": "blanc",
  "description": "Inspired by Omut’s jewelry collections, this series explores the interplay of ice and metal, translating the brand’s bold aesthetic into sculptural forms, sharp details, and reflective surfaces.",
  "cover": "/media/omut/01.jpg",
  "marquee": [
    { "type": "image", "src": "/media/omut/01.jpg" },
    { "type": "image", "src": "/media/omut/04.jpg" },
    { "type": "image", "src": "/media/omut/03.jpg" },
    { "type": "text" },
    { "type": "image", "src": "/media/omut/02.jpg" },
    { "type": "image", "src": "/media/omut/05.jpg" },
    { "type": "image", "src": "/media/omut/06.jpg" }
  ],
  "gallery": [
    { "type": "image", "src": "/media/omut/01.jpg", "cols": 1 },
    { "type": "image", "src": "/media/omut/02.jpg", "cols": 2, "pair": "/media/omut/03.jpg" },
    { "type": "image", "src": "/media/omut/04.jpg", "cols": 1 },
    { "type": "image", "src": "/media/omut/05.jpg", "cols": 2, "pair": "/media/omut/06.jpg" }
  ]
}
